promptpilot/__init__.py
promptpilot/cli.py
promptpilot/formatters/__init__.py
promptpilot/formatters/base.py
promptpilot/formatters/json.py
promptpilot/formatters/text.py
promptpilot/models/__init__.py
promptpilot/models/prompt.py
promptpilot/providers/__init__.py
promptpilot/providers/base.py
promptpilot/providers/claude_provider.py
promptpilot/providers/hf_provider.py
promptpilot/providers/llama_provider.py
promptpilot/providers/openai_provider.py
promptpilot/runner/__init__.py
promptpilot/runner/abtest.py
promptpilot/runner/batch.py
promptpilot/runner/multi_prompt.py
promptpilot/utils.py
promptpilot/versioning.py
promptpilot_cli-0.0.1.dist-info/LICENSE.md
promptpilot_cli-0.0.1.dist-info/METADATA
promptpilot_cli-0.0.1.dist-info/WHEEL
promptpilot_cli-0.0.1.dist-info/entry_points.txt
promptpilot_cli-0.0.1.dist-info/RECORD
