Metadata-Version: 2.3
Name: promptpilot-cli
Version: 0.0.1
Summary: CLI for prompt versioning and A/B testing across AI providers
License: MIT
Author: Arif Dogan
Author-email: me@arif.sh
Requires-Python: >=3.11
Classifier: License :: OSI Approved :: MIT License
Classifier: Programming Language :: Python :: 3
Classifier: Programming Language :: Python :: 3.11
Classifier: Programming Language :: Python :: 3.12
Classifier: Programming Language :: Python :: 3.13
Requires-Dist: anthropic (>=0.49.0,<0.50.0)
Requires-Dist: click (>=8.1.8,<9.0.0)
Requires-Dist: gitpython (>=3.1.44,<4.0.0)
Requires-Dist: openai (>=1.75.0,<2.0.0)
Requires-Dist: pytest (>=8.3.5,<9.0.0)
Requires-Dist: pytest-cov (>=6.1.1,<7.0.0)
Requires-Dist: python-dotenv (>=1.1.0,<2.0.0)
Requires-Dist: pyyaml (>=6.0.2,<7.0.0)
Requires-Dist: torch (>=2.6.0,<3.0.0)
Requires-Dist: transformers (>=4.51.3,<5.0.0)
